MANIFEST.in
README.md
setup.cfg
setup.py
django_roles/__init__.py
django_roles/admin.py
django_roles/forms.py
django_roles/managers.py
django_roles/models.py
django_roles.egg-info/PKG-INFO
django_roles.egg-info/SOURCES.txt
django_roles.egg-info/dependency_links.txt
django_roles.egg-info/not-zip-safe
django_roles.egg-info/requires.txt
django_roles.egg-info/top_level.txt
django_roles/backends/__init__.py
django_roles/backends/bottomup_role_authenticate_backend.py
django_roles/backends/role_authenticate_backend.py