Metadata-Version: 1.1
Name: django-roles
Version: 0.0.3
Summary: Django Roles with Role-Group-Permission-User
Home-page: https://github.com/cenkbircanoglu/django-roles
Author: Cenk Bircanoglu
Author-email: cenk.bircanoglu@gmail.com
License: MIT
Download-URL: https://github.com/cenkbircanoglu/django_roles/tarball/0.0.3
Keywords: django,auth,user,user role,user role,organization,python
Platform: any
